cortexgraph/__init__.py
cortexgraph/background.py
cortexgraph/config.py
cortexgraph/context.py
cortexgraph/performance.py
cortexgraph/server.py
cortexgraph/backup/__init__.py
cortexgraph/backup/git_backup.py
cortexgraph/cli/__init__.py
cortexgraph/cli/migrate.py
cortexgraph/core/__init__.py
cortexgraph/core/clustering.py
cortexgraph/core/consolidation.py
cortexgraph/core/decay.py
cortexgraph/core/pagination.py
cortexgraph/core/review.py
cortexgraph/core/scoring.py
cortexgraph/integration/__init__.py
cortexgraph/integration/basic_memory.py
cortexgraph/security/__init__.py
cortexgraph/security/paths.py
cortexgraph/security/permissions.py
cortexgraph/security/secrets.py
cortexgraph/security/validators.py
cortexgraph/storage/__init__.py
cortexgraph/storage/jsonl_storage.py
cortexgraph/storage/ltm_index.py
cortexgraph/storage/maintenance.py
cortexgraph/storage/models.py
cortexgraph/tools/__init__.py
cortexgraph/tools/cluster.py
cortexgraph/tools/consolidate.py
cortexgraph/tools/create_relation.py
cortexgraph/tools/gc.py
cortexgraph/tools/observe.py
cortexgraph/tools/open_memories.py
cortexgraph/tools/performance.py
cortexgraph/tools/promote.py
cortexgraph/tools/read_graph.py
cortexgraph/tools/save.py
cortexgraph/tools/search.py
cortexgraph/tools/search_unified.py
cortexgraph/tools/touch.py
cortexgraph/vault/__init__.py
cortexgraph/vault/markdown_writer.py
cortexgraph_fastmcp-0.2.2.dist-info/METADATA
cortexgraph_fastmcp-0.2.2.dist-info/WHEEL
cortexgraph_fastmcp-0.2.2.dist-info/entry_points.txt
cortexgraph_fastmcp-0.2.2.dist-info/licenses/LICENSE
cortexgraph_fastmcp-0.2.2.dist-info/RECORD
